mlx_hubert/__init__.py
mlx_hubert/config.py
mlx_hubert/layers.py
mlx_hubert/model.py
mlx_hubert/processor.py
mlx_hubert/utils.py
mlx_hubert-0.1.0.dist-info/licenses/LICENSE
mlx_hubert-0.1.0.dist-info/METADATA
mlx_hubert-0.1.0.dist-info/WHEEL
mlx_hubert-0.1.0.dist-info/top_level.txt
mlx_hubert-0.1.0.dist-info/RECORD
