Metadata-Version: 2.4
Name: mlx_hubert
Version: 0.1.0
Summary: HuBERT (Hidden Unit BERT) implementation in MLX for Apple Silicon
Home-page: https://github.com/ml-explore/mlx-hubert
Author: MLX Community
Author-email: 
License: MIT
Project-URL: Homepage, https://github.com/mzbac/mlx-hubert
Project-URL: Documentation, https://github.com/mzbac/mlx-hubert#readme
Project-URL: Repository, https://github.com/mzbac/mlx-hubert
Project-URL: Issues, https://github.com/mzbac/mlx-hubert/issues
Keywords: mlx,hubert,speech-recognition,asr,apple-silicon,machine-learning
Classifier: Development Status :: 3 - Alpha
Classifier: Intended Audience :: Developers
Classifier: Intended Audience :: Science/Research
Classifier: License :: OSI Approved :: MIT License
Classifier: Topic :: Scientific/Engineering :: Artificial Intelligence
Classifier: Topic :: Multimedia :: Sound/Audio :: Speech
Classifier: Programming Language :: Python :: 3
Classifier: Programming Language :: Python :: 3.8
Classifier: Programming Language :: Python :: 3.9
Classifier: Programming Language :: Python :: 3.10
Classifier: Programming Language :: Python :: 3.11
Classifier: Programming Language :: Python :: 3.12
Requires-Python: >=3.8
License-File: LICENSE
Requires-Dist: mlx>=0.14.0
Requires-Dist: numpy>=1.21.0
Requires-Dist: safetensors>=0.4.0
Requires-Dist: huggingface-hub>=0.19.0
Requires-Dist: tqdm>=4.65.0
Requires-Dist: datasets>=2.14.4
Requires-Dist: torch>=2.5.1
Requires-Dist: torchcodec>=0.5
Requires-Dist: soundfile>=0.13.1
Provides-Extra: dev
Requires-Dist: pytest>=7.0.0; extra == "dev"
Requires-Dist: pytest-cov>=4.0.0; extra == "dev"
Requires-Dist: black>=22.0.0; extra == "dev"
Requires-Dist: isort>=5.0.0; extra == "dev"
Requires-Dist: flake8>=4.0.0; extra == "dev"
Requires-Dist: mypy>=0.950; extra == "dev"
Provides-Extra: examples
Requires-Dist: datasets>=2.0.0; extra == "examples"
Requires-Dist: soundfile>=0.12.0; extra == "examples"
Requires-Dist: librosa>=0.10.0; extra == "examples"
Provides-Extra: all
Requires-Dist: mlx-hubert[dev,examples]; extra == "all"
Dynamic: home-page
Dynamic: license-file
Dynamic: requires-python
